odoo/addons/printer_custom_options/README.rst
odoo/addons/printer_custom_options/__init__.py
odoo/addons/printer_custom_options/__manifest__.py
odoo/addons/printer_custom_options/i18n/printer_custom_options.pot
odoo/addons/printer_custom_options/models/__init__.py
odoo/addons/printer_custom_options/models/printer_option.py
odoo/addons/printer_custom_options/models/printer_option_choice.py
odoo/addons/printer_custom_options/models/printing_printer.py
odoo/addons/printer_custom_options/models/report_xml.py
odoo/addons/printer_custom_options/readme/CONTRIBUTORS.rst
odoo/addons/printer_custom_options/readme/DESCRIPTION.rst
odoo/addons/printer_custom_options/readme/USAGE.rst
odoo/addons/printer_custom_options/security/ir.model.access.csv
odoo/addons/printer_custom_options/static/description/icon.png
odoo/addons/printer_custom_options/static/description/index.html
odoo/addons/printer_custom_options/tests/__init__.py
odoo/addons/printer_custom_options/tests/test_printing_printer.py
odoo/addons/printer_custom_options/views/ir_actions_reports_xml_view.xml
odoo/addons/printer_custom_options/views/printing_printer.xml
odoo11_addon_printer_custom_options-11.0.1.0.0.dist-info/METADATA
odoo11_addon_printer_custom_options-11.0.1.0.0.dist-info/WHEEL
odoo11_addon_printer_custom_options-11.0.1.0.0.dist-info/top_level.txt
odoo11_addon_printer_custom_options-11.0.1.0.0.dist-info/RECORD
