Metadata-Version: 2.1
Name: odoo11-addon-printer-custom-options
Version: 11.0.1.0.0
Summary: Adds the ability to check all printing options available from a CUPS printer set them in the reports
Home-page: https://github.com/OCA/report-print-send
Author: Compassion CH, OCA
License: AGPL-3
Platform: UNKNOWN
Classifier: Programming Language :: Python
Classifier: Framework :: Odoo
Classifier: License :: OSI Approved :: GNU Affero General Public License v3
Requires-Python: >=2.7, !=3.0.*, !=3.1.*, !=3.2.*, !=3.3.*, !=3.4.*
Requires-Dist: odoo11-addon-base-report-to-printer
Requires-Dist: odoo (<11.1dev,>=11.0a)
Requires-Dist: pycups
